{
	"version":1.0,
	"people":[
		{
			"pose_keypoints":[
				0,0,0,0,0,0,682.836,305.187,0.191705,729.778,401.102,0.744366,833.451,532.172,0.56425,0,0,0,0,0,0,0,0,0,0,0,0,0,0,0,0,0,0,0,0,0,0,0,0,0,0,0,0,0,0,0,0,0,0,0,0,0,0,0
			],
			"face_keypoints":[
				
			],
			"hand_left_keypoints":[
				
			],
			"hand_right_keypoints":[
				
			]
		},
		{
			"pose_keypoints":[
				0,0,0,0,0,0,606.507,369.788,0.152746,539.945,536.082,0.51625,538.03,665.262,0.204483,0,0,0,0,0,0,0,0,0,0,0,0,0,0,0,0,0,0,0,0,0,0,0,0,0,0,0,0,0,0,0,0,0,0,0,0,0,0,0
			],
			"face_keypoints":[
				
			],
			"hand_left_keypoints":[
				
			],
			"hand_right_keypoints":[
				
			]
		},
		{
			"pose_keypoints":[
				0,0,0,637.841,303.267,0.250793,0,0,0,0,0,0,0,0,0,0,0,0,0,0,0,0,0,0,352.203,322.822,0.232622,446.056,588.899,0.586931,328.706,584.993,0.0702097,430.422,391.302,0.1459,471.54,588.914,0.09787,0,0,0,0,0,0,0,0,0,0,0,0,0,0,0
			],
			"face_keypoints":[
				
			],
			"hand_left_keypoints":[
				
			],
			"hand_right_keypoints":[
				
			]
		}
	]
}
